django_two_factor_auth_ovh_gateway/__init__.py
django_two_factor_auth_ovh_gateway/apps.py
django_two_factor_auth_ovh_gateway/conf/__init__.py
django_two_factor_auth_ovh_gateway/conf/settings.py
django_two_factor_auth_ovh_gateway/gateway.py
django_two_factor_auth_ovh_gateway-0.0.3.dist-info/LICENSE
django_two_factor_auth_ovh_gateway-0.0.3.dist-info/METADATA
django_two_factor_auth_ovh_gateway-0.0.3.dist-info/WHEEL
django_two_factor_auth_ovh_gateway-0.0.3.dist-info/RECORD
