Metadata-Version: 2.1
Name: django_two_factor_auth_ovh_gateway
Version: 0.0.3
Summary: Extension for django-two-factor-auth to use OVH SMS gateway
Home-page: https://gitlab.com/kapt/open-source/django-two-factor-auth-ovh-gateway
License: GNU GPLv3
Author: Kapt dev team
Author-email: dev@kapt.mobi
Requires-Python: >=3.10,<4.0
Classifier: License :: Other/Proprietary License
Classifier: Programming Language :: Python :: 3
Classifier: Programming Language :: Python :: 3.10
Classifier: Programming Language :: Python :: 3.11
Classifier: Programming Language :: Python :: 3.12
Requires-Dist: Django (>=3.0,<4.0)
Requires-Dist: django-two-factor-auth[phonenumbers] (>=1.15.2,<2.0.0)
Requires-Dist: ovh (>=1.1.0,<2.0.0)
Project-URL: Repository, https://gitlab.com/kapt/open-source/django-two-factor-auth-ovh-gateway
